{
  "resourceType": "Bundle",
  "type": "collection",
  "entry": [
    {
      "resource": {
        "resourceType": "Patient",
        "id": "patient-60",
        "name": [
          {
            "given": [
              "Patient_60"
            ],
            "family": "Synthea"
          }
        ],
        "gender": "female",
        "birthDate": "1955-09-07",
        "address": [
          {
            "city": "Boston",
            "state": "MA",
            "country": "US"
          }
        ]
      }
    },
    {
      "resource": {
        "resourceType": "Observation",
        "id": "86a4c51e-2589-4517-bbad-93e10bdbb4ac",
        "status": "final",
        "code": {
          "coding": [
            {
              "system": "http://loinc.org",
              "code": "89204-2"
            }
          ]
        },
        "subject": {
          "reference": "Patient/patient-60"
        },
        "effectiveDateTime": "2025-06-05T12:52:22.458639",
        "valueQuantity": {
          "value": 8.9,
          "unit": "g/dL",
          "system": "http://unitsofmeasure.org",
          "code": "g/dL"
        }
      }
    },
    {
      "resource": {
        "resourceType": "Observation",
        "id": "7642883a-dea3-44b7-8a25-dea1d2b718e5",
        "status": "final",
        "code": {
          "coding": [
            {
              "system": "http://loinc.org",
              "code": "79888-4"
            }
          ]
        },
        "subject": {
          "reference": "Patient/patient-60"
        },
        "effectiveDateTime": "2025-05-12T12:52:22.458639",
        "valueQuantity": {
          "value": 12.5,
          "unit": "g/dL",
          "system": "http://unitsofmeasure.org",
          "code": "g/dL"
        }
      }
    },
    {
      "resource": {
        "resourceType": "Observation",
        "id": "f81e6c6b-a12a-451e-873d-e307fdf4652f",
        "status": "final",
        "code": {
          "coding": [
            {
              "system": "http://loinc.org",
              "code": "79888-4"
            }
          ]
        },
        "subject": {
          "reference": "Patient/patient-60"
        },
        "effectiveDateTime": "2026-04-14T12:52:22.458639",
        "valueQuantity": {
          "value": 12.6,
          "unit": "g/dL",
          "system": "http://unitsofmeasure.org",
          "code": "g/dL"
        }
      }
    },
    {
      "resource": {
        "resourceType": "Observation",
        "id": "3ff5337a-ad91-4396-9bd5-1c6a342049b1",
        "status": "final",
        "code": {
          "coding": [
            {
              "system": "http://loinc.org",
              "code": "79893-4"
            }
          ]
        },
        "subject": {
          "reference": "Patient/patient-60"
        },
        "effectiveDateTime": "2026-04-24T12:52:22.458639",
        "valueQuantity": {
          "value": 12.7,
          "unit": "g/dL",
          "system": "http://unitsofmeasure.org",
          "code": "g/dL"
        }
      }
    },
    {
      "resource": {
        "resourceType": "Observation",
        "id": "dc9deabd-5353-46e9-a52f-6b1ce27e383c",
        "status": "final",
        "code": {
          "coding": [
            {
              "system": "http://loinc.org",
              "code": "79888-4"
            }
          ]
        },
        "subject": {
          "reference": "Patient/patient-60"
        },
        "effectiveDateTime": "2025-05-16T12:52:22.458639",
        "valueQuantity": {
          "value": 9.7,
          "unit": "g/dL",
          "system": "http://unitsofmeasure.org",
          "code": "g/dL"
        }
      }
    },
    {
      "resource": {
        "resourceType": "Observation",
        "id": "68992d0d-1cd4-4880-b594-d5b325b0120b",
        "status": "final",
        "code": {
          "coding": [
            {
              "system": "http://loinc.org",
              "code": "79893-4"
            }
          ]
        },
        "subject": {
          "reference": "Patient/patient-60"
        },
        "effectiveDateTime": "2026-02-23T12:52:22.458639",
        "valueQuantity": {
          "value": 12.0,
          "unit": "g/dL",
          "system": "http://unitsofmeasure.org",
          "code": "g/dL"
        }
      }
    },
    {
      "resource": {
        "resourceType": "Observation",
        "id": "bd1ed7cf-ec3e-4cfa-b76b-afd6e0f0e663",
        "status": "final",
        "code": {
          "coding": [
            {
              "system": "http://loinc.org",
              "code": "49551-5"
            }
          ]
        },
        "subject": {
          "reference": "Patient/patient-60"
        },
        "effectiveDateTime": "2025-11-21T12:52:22.458639",
        "valueQuantity": {
          "value": 14.7,
          "unit": "g/dL",
          "system": "http://unitsofmeasure.org",
          "code": "g/dL"
        }
      }
    },
    {
      "resource": {
        "resourceType": "Observation",
        "id": "e484be00-a6af-401f-9601-a507534e3541",
        "status": "final",
        "code": {
          "coding": [
            {
              "system": "http://loinc.org",
              "code": "79888-4"
            }
          ]
        },
        "subject": {
          "reference": "Patient/patient-60"
        },
        "effectiveDateTime": "2025-08-24T12:52:22.458639",
        "valueQuantity": {
          "value": 10.5,
          "unit": "g/dL",
          "system": "http://unitsofmeasure.org",
          "code": "g/dL"
        }
      }
    }
  ]
}